deciphonctl/__init__.py
deciphonctl/__main__.py
deciphonctl/catch_validation.py
deciphonctl/cli.py
deciphonctl/display_exception.py
deciphonctl/log_level.py
deciphonctl/progress.py
deciphonctl/settings.py
deciphonctl/url.py
deciphonctl-1.0.1.dist-info/LICENSE
deciphonctl-1.0.1.dist-info/METADATA
deciphonctl-1.0.1.dist-info/WHEEL
deciphonctl-1.0.1.dist-info/entry_points.txt
deciphonctl-1.0.1.dist-info/RECORD
