Metadata-Version: 2.1
Name: deciphonctl
Version: 1.0.1
Summary: Control Deciphon server.
License: MIT
Author: Danilo Horta
Author-email: horta@ebi.ac.uk
Requires-Python: >=3.10,<4.0
Classifier: License :: OSI Approved :: MIT License
Classifier: Programming Language :: Python :: 3
Classifier: Programming Language :: Python :: 3.10
Classifier: Programming Language :: Python :: 3.11
Classifier: Programming Language :: Python :: 3.12
Classifier: Programming Language :: Python :: 3.13
Requires-Dist: deciphon (>=1.0.3,<2.0.0)
Requires-Dist: deciphon-poster (>=0.2.2,<0.3.0)
Requires-Dist: fasta-reader (>=3.0.3,<4.0.0)
Requires-Dist: loguru (>=0.7,<0.8)
Requires-Dist: paho-mqtt (>=2.1,<3.0)
Requires-Dist: pydantic (>=2.9,<3.0)
Requires-Dist: pydantic-settings (>=2.5,<3.0)
Requires-Dist: python-dotenv (>=1.0.1,<2.0.0)
Requires-Dist: requests (>=2.32,<3.0)
Requires-Dist: requests-toolbelt (>=1.0,<2.0)
Requires-Dist: typer (>=0.12,<0.13)
Requires-Dist: xdg-base-dirs (>=6.0.2,<7.0.0)
